fastpathplanning/__init__.py
fastpathplanning/boxes.py
fastpathplanning/fastpathplanning.py
fastpathplanning/graph.py
fastpathplanning/polygonal.py
fastpathplanning/smooth.py
fastpathplanning-0.1.2.dist-info/LICENSE
fastpathplanning-0.1.2.dist-info/METADATA
fastpathplanning-0.1.2.dist-info/WHEEL
fastpathplanning-0.1.2.dist-info/top_level.txt
fastpathplanning-0.1.2.dist-info/RECORD
