Metadata-Version: 2.1
Name: fastpathplanning
Version: 0.1.2
Summary: An algorithm for path planning in sequences of safe boxes
Home-page: https://github.com/cvxgrp/fpp.py
License: UNKNOWN
Platform: UNKNOWN
Classifier: Programming Language :: Python :: 3
License-File: LICENSE
Requires-Dist: cvxpy
Requires-Dist: networkx
Requires-Dist: numpy (>=1.17.5)
Requires-Dist: scipy
